LICENSE
PKG-INFO
admin.jpg
dev.cfg
dolint.bat
dolint.py
prod.cfg
pylintrc
setup.py
start-turboblog.py
docs/install.odt
docs/install.pdf
docs/usermanual.odt
docs/usermanual.pdf
plugins/sidebar/recentposts/setup.py
plugins/sidebar/recentposts/RecentPosts.egg-info/PKG-INFO
plugins/sidebar/recentposts/RecentPosts.egg-info/SOURCES.txt
plugins/sidebar/recentposts/RecentPosts.egg-info/entry_points.txt
plugins/sidebar/recentposts/RecentPosts.egg-info/not-zip-safe
plugins/sidebar/recentposts/RecentPosts.egg-info/top_level.txt
plugins/sidebar/recentposts/recentposts/__init__.py
plugins/sidebar/recentposts/recentposts/plugin.py
plugins/sidebar/shoutbox/setup.py
plugins/sidebar/shoutbox/ShoutBox.egg-info/PKG-INFO
plugins/sidebar/shoutbox/ShoutBox.egg-info/SOURCES.txt
plugins/sidebar/shoutbox/ShoutBox.egg-info/entry_points.txt
plugins/sidebar/shoutbox/ShoutBox.egg-info/not-zip-safe
plugins/sidebar/shoutbox/ShoutBox.egg-info/top_level.txt
plugins/sidebar/shoutbox/shoutbox/__init__.py
plugins/sidebar/shoutbox/shoutbox/plugin.py
turboblog/__init__.py
turboblog/admincontrol.py
turboblog/antispam.py
turboblog/controllers.py
turboblog/formdisplay.py
turboblog/forms.py
turboblog/gravatar.py
turboblog/json.py
turboblog/model.py
turboblog/pager.py
turboblog/plugins.py
turboblog/rpccontroller.py
turboblog/trackback.py
turboblog.egg-info/PKG-INFO
turboblog.egg-info/SOURCES.txt
turboblog.egg-info/dependency_links.txt
turboblog.egg-info/not-zip-safe
turboblog.egg-info/requires.txt
turboblog.egg-info/top_level.txt
turboblog/config/__init__.py
turboblog/config/app.cfg
turboblog/config/log.cfg
turboblog/data/freesans.ttf
turboblog/static/css/admin.css
turboblog/static/css/livesearch.css
turboblog/static/css/register.css
turboblog/static/css/style.css
turboblog/static/css/undohtml.css
turboblog/static/css/marinee/style.css
turboblog/static/images/dot-top.gif
turboblog/static/images/dot.gif
turboblog/static/images/fade-butt.png
turboblog/static/images/favicon.ico
turboblog/static/images/kubrickbg.jpg
turboblog/static/images/kubrickbgcolor.jpg
turboblog/static/images/kubrickbgwide.jpg
turboblog/static/images/kubrickfooter.jpg
turboblog/static/images/kubrickheader.jpg
turboblog/static/images/oddlogo.png
turboblog/static/images/backgrounds/arrow.png
turboblog/static/images/backgrounds/body.gif
turboblog/static/images/backgrounds/comment.png
turboblog/static/images/backgrounds/comment_hover.png
turboblog/static/images/backgrounds/h1.png
turboblog/static/images/backgrounds/h1_hover.png
turboblog/static/images/backgrounds/submenua.jpg
turboblog/static/images/backgrounds/submenua_normal.jpg
turboblog/static/images/marinee/bg.gif
turboblog/static/images/marinee/blockquote.png
turboblog/static/images/marinee/dot.gif
turboblog/static/images/marinee/favicon.ico
