Metadata-Version: 1.0
Name: turboblog
Version: 1.0.2
Summary: Blogging platform for TurboGears
Home-page: http://turboblog.devjavu.com/
Author: Eli Yukelzon, Florent Aide
Author-email: reflog@gmail.com, florent.aide@gmail.com
License: MIT
Download-URL: http://cheeseshop.python.org/packages/2.4/t/turboblog/turboblog-1.0.2-py2.4.egg
Keywords: turbogears.app
Platform: UNKNOWN
Classifier: Development Status :: 3 - Alpha
Classifier: Environment :: Console
Classifier: Intended Audience :: Developers
Classifier: License :: OSI Approved :: MIT License
Classifier: Operating System :: OS Independent
Classifier: Programming Language :: Python
Classifier: Topic :: Software Development :: Libraries :: Python Modules
Classifier: Framework :: TurboGears :: Applications
